Metadata-Version: 1.0
Name: myfirstdemo2
Version: 1.0.0
Summary: test_demo
Home-page: http://www.haocang.com
Author: hc
Author-email: crystal910901@foxmail.com
License: MIT
Platform: UNKNOWN
